xcals/__init__.py
xcals/api.py
xcals-0.1.6.dist-info/METADATA
xcals-0.1.6.dist-info/WHEEL
xcals-0.1.6.dist-info/top_level.txt
xcals-0.1.6.dist-info/RECORD
