Metadata-Version: 2.1
Name: xcals
Version: 0.1.6
Summary: A股交易日历以及日内交易时间
Project-URL: homepage, https://github.com/link-yundi/xcals
Project-URL: repository, https://github.com/link-yundi/xcals
Requires-Python: >=3.8
Requires-Dist: pandas>=2.0.3
